{
  "runTime": 1667864497212,
  "source": {
    "band_list": [
      {
        "raw_hot": 1751138,
        "num": 1751138,
        "word": "消费者称李佳琦直播间产品比官方贵",
        "onboard_time": 1667830050,
        "rank": 0,
        "category": "社会新闻,网红"
      },
      {
        "raw_hot": 815302,
        "num": 815302,
        "word": "韩国踩踏事故6人被立案调查",
        "onboard_time": 1667846532,
        "rank": 1,
        "category": "社会新闻"
      },
      {
        "raw_hot": 6912,
        "num": 485656,
        "word": "携手构建网络空间命运共同体白皮书发布会",
        "onboard_time": 1667795743,
        "rank": 2,
        "category": "国内要闻"
      },
      {
        "raw_hot": 482238,
        "num": 482238,
        "word": "史上最凶班主任经证实为网红",
        "onboard_time": 1667823625,
        "rank": 3,
        "category": "社会新闻,教育"
      },
      {
        "raw_hot": 454343,
        "num": 454343,
        "word": "手机厂商集体大降价",
        "onboard_time": 1667835150,
        "rank": 4,
        "category": "科技,财经"
      },
      {
        "raw_hot": 424155,
        "num": 424155,
        "word": "俞敏洪称10年吃了3000片安眠药",
        "onboard_time": 1667829447,
        "rank": 5,
        "category": "社会新闻"
      },
      {
        "raw_hot": 401911,
        "num": 401911,
        "word": "新疆新增无症状感染者585例",
        "onboard_time": 1667852952,
        "rank": 6,
        "category": "社会新闻"
      },
      {
        "raw_hot": 330668,
        "num": 330668,
        "word": "95后女孩瘫痪20年自学捏粘土售卖",
        "onboard_time": 1667857211,
        "rank": 7,
        "category": "社会新闻"
      },
      {
        "raw_hot": 328505,
        "num": 328505,
        "word": "央视曝光双十一新骗术",
        "onboard_time": 1667817448,
        "rank": 8,
        "category": "社会新闻"
      },
      {
        "raw_hot": 285596,
        "num": 285596,
        "word": "中方回应日本加入北约网络防御中心",
        "onboard_time": 1667832811,
        "rank": 9,
        "category": "国内要闻"
      },
      {
        "raw_hot": 553676,
        "num": 282107,
        "word": "黄婷婷被判与丝芭传媒解约",
        "onboard_time": 1667835029,
        "rank": 10,
        "category": "艺人"
      },
      {
        "raw_hot": 266784,
        "num": 266784,
        "word": "熊孩子喊饿趁妈妈睡觉点300多元外卖",
        "onboard_time": 1667830649,
        "rank": 11,
        "category": "社会新闻"
      },
      {
        "raw_hot": 226283,
        "num": 226283,
        "word": "家中起火白狗熏成黑狗趴窗求救",
        "onboard_time": 1667835628,
        "rank": 12,
        "category": "社会新闻"
      },
      {
        "raw_hot": 210207,
        "num": 210207,
        "word": "马斯克解雇了90%的印度推特员工",
        "onboard_time": 1667824286,
        "rank": 13,
        "category": "科技,社会新闻"
      },
      {
        "raw_hot": 198310,
        "num": 198310,
        "word": "广州海珠区社会面疫情防控延长至11日",
        "onboard_time": 1667843175,
        "rank": 14,
        "category": "社会新闻"
      },
      {
        "raw_hot": 194568,
        "num": 194568,
        "word": "5男子饭馆吃133元要求少收100元",
        "onboard_time": 1667826688,
        "rank": 15,
        "category": "社会新闻"
      },
      {
        "raw_hot": 191205,
        "num": 191205,
        "word": "韩国短道选手回应挑衅手势",
        "onboard_time": 1667831669,
        "rank": 16,
        "category": "体育"
      },
      {
        "raw_hot": 185465,
        "num": 185465,
        "word": "北京12345回应",
        "onboard_time": 1667832096,
        "rank": 17,
        "category": "社会新闻"
      },
      {
        "raw_hot": 178469,
        "num": 178469,
        "word": "王一博今日直播截图状态",
        "onboard_time": 1667835628,
        "rank": 18,
        "category": "艺人"
      },
      {
        "raw_hot": 164496,
        "num": 164496,
        "word": "25岁爸爸带娃一年日渐沧桑",
        "onboard_time": 1667823448,
        "rank": 19,
        "category": "社会新闻"
      },
      {
        "raw_hot": 158598,
        "num": 158598,
        "word": "全国近八成地级及以上城市房价不过万",
        "onboard_time": 1667825426,
        "rank": 20,
        "category": "财经,社会新闻"
      },
      {
        "raw_hot": 141354,
        "num": 141354,
        "word": "外交部回应七国集团外长会声明",
        "onboard_time": 1667851992,
        "rank": 21,
        "category": "国内要闻"
      },
      {
        "raw_hot": 139605,
        "num": 139605,
        "word": "小伙网恋被骗后加入对方被判缓刑",
        "onboard_time": 1667852711,
        "rank": 22,
        "category": "社会新闻"
      },
      {
        "raw_hot": 133085,
        "num": 133085,
        "word": "血月",
        "onboard_time": 1667828668,
        "rank": 23,
        "category": "自然"
      },
      {
        "raw_hot": 129652,
        "num": 129652,
        "word": "为什么很多人不愿意恋爱了",
        "onboard_time": 1667839701,
        "rank": 24,
        "category": "情感"
      },
      {
        "raw_hot": 127683,
        "num": 127683,
        "word": "朱韵真的是公主殿下",
        "onboard_time": 1667822965,
        "rank": 25,
        "category": "影视"
      },
      {
        "raw_hot": 110039,
        "num": 110039,
        "word": "乌鲁木齐警情通报",
        "onboard_time": 1667817626,
        "rank": 26,
        "category": "社会新闻"
      },
      {
        "raw_hot": 110607,
        "num": 108843,
        "word": "公主 你当我是豆腐做的",
        "onboard_time": 1667843475,
        "rank": 27,
        "category": "影视"
      },
      {
        "raw_hot": 103937,
        "num": 103937,
        "word": "江西的早餐有多便宜",
        "onboard_time": 1667834610,
        "rank": 28,
        "category": "美食"
      },
      {
        "raw_hot": 99439,
        "num": 99439,
        "word": "小伙患红斑狼疮近5年爬楼超10万层",
        "onboard_time": 1667815887,
        "rank": 29,
        "category": "社会新闻"
      },
      {
        "raw_hot": 132345,
        "num": 97958,
        "word": "嫌打篮球太吵老人从7楼扔饮料瓶",
        "onboard_time": 1667864123,
        "rank": 30,
        "category": "社会新闻"
      },
      {
        "raw_hot": 114310,
        "num": 97724,
        "word": "鲸整口吞下一群鱼画面太震撼",
        "onboard_time": 1667864008,
        "rank": 31,
        "category": "社会新闻"
      },
      {
        "raw_hot": 95799,
        "num": 95799,
        "word": "老人患阿兹海默病与镜中自己聊天",
        "onboard_time": 1667863340,
        "rank": 32,
        "category": "社会新闻"
      },
      {
        "raw_hot": 93647,
        "num": 93647,
        "word": "全球人口将达80亿",
        "onboard_time": 1667849051,
        "rank": 33,
        "category": "社会新闻"
      },
      {
        "raw_hot": 90646,
        "num": 90646,
        "word": "台北故宫文物毁损视频首曝光",
        "onboard_time": 1667825547,
        "rank": 34,
        "category": "社会新闻"
      },
      {
        "raw_hot": 86514,
        "num": 86514,
        "word": "小伙清理舌苔误吞18厘米长牙刷",
        "onboard_time": 1667863883,
        "rank": 35,
        "category": "社会新闻"
      },
      {
        "raw_hot": 82966,
        "num": 82966,
        "word": "吃不到肉被气哭的猫咪",
        "onboard_time": 1667831191,
        "rank": 36,
        "category": "幽默"
      },
      {
        "raw_hot": 82138,
        "num": 82138,
        "word": "李峋排球课后晕倒了",
        "onboard_time": 1667832282,
        "rank": 37,
        "category": "影视"
      },
      {
        "raw_hot": 81300,
        "num": 81300,
        "word": "经得起寸头检验的男星",
        "onboard_time": 1667837366,
        "rank": 38,
        "category": "作品衍生"
      },
      {
        "raw_hot": 66810,
        "num": 66810,
        "word": "AJ涵艺爆料LPL转会期",
        "onboard_time": 1667818167,
        "rank": 39,
        "category": "游戏"
      },
      {
        "raw_hot": 64885,
        "num": 64885,
        "word": "航拍中国第四季",
        "onboard_time": 1667864426,
        "rank": 40,
        "category": "影视"
      },
      {
        "raw_hot": 64140,
        "num": 64140,
        "word": "3岁萌娃欺负姐妹爸爸竹鞭打床吓哭",
        "onboard_time": 1667863402,
        "rank": 41,
        "category": "社会新闻"
      },
      {
        "raw_hot": 63780,
        "num": 63780,
        "word": "雷佳音回应感言说一半话筒掉了",
        "onboard_time": 1667813846,
        "rank": 42,
        "category": "影视"
      },
      {
        "raw_hot": 63081,
        "num": 63081,
        "word": "李峋吃醋",
        "onboard_time": 1667824648,
        "rank": 43,
        "category": "影视"
      },
      {
        "raw_hot": 55238,
        "num": 55238,
        "word": "外资开始抄底房地产",
        "onboard_time": 1667812108,
        "rank": 44,
        "category": "财经"
      },
      {
        "raw_hot": 54074,
        "num": 54074,
        "word": "厦门海关截获1只活体黑寡妇",
        "onboard_time": 1667805806,
        "rank": 45,
        "category": "社会新闻"
      },
      {
        "raw_hot": 50785,
        "num": 50785,
        "word": "机器人和消防员合力救下溺海女子",
        "onboard_time": 1667864241,
        "rank": 46,
        "category": "社会新闻"
      },
      {
        "raw_hot": 50419,
        "num": 50419,
        "word": "赵露思偷偷藏不住杀青视频",
        "onboard_time": 1667835628,
        "rank": 47,
        "category": "影视"
      },
      {
        "raw_hot": 49212,
        "num": 49212,
        "word": "月全食",
        "onboard_time": 1667816126,
        "rank": 48,
        "category": "自然,社会新闻"
      },
      {
        "raw_hot": 49100,
        "num": 49100,
        "word": "韩剧想你首播10周年",
        "onboard_time": 1667848932,
        "rank": 49,
        "category": "影视"
      }
    ],
    "hotgov": {
      "word": "#直击2022中国航展#"
    }
  }
}