{
  "runTime": 1668939738517,
  "source": {
    "band_list": [
      {
        "raw_hot": 1373505,
        "num": 1373505,
        "word": "江西16岁失联男孩已找到",
        "onboard_time": 1668928105,
        "rank": 0,
        "category": "社会新闻"
      },
      {
        "raw_hot": 1213184,
        "num": 1213184,
        "word": "男子出车祸600私了6天后大出血死亡",
        "onboard_time": 1668923787,
        "rank": 1,
        "category": "社会负面"
      },
      {
        "raw_hot": 45464,
        "num": 1151570,
        "word": "绝美视角看神十四太空漫步",
        "onboard_time": 1668927566,
        "rank": 2,
        "category": "国内要闻"
      },
      {
        "raw_hot": 1144940,
        "num": 1144940,
        "word": "北京新增516例本土感染者",
        "onboard_time": 1668936447,
        "rank": 3,
        "category": "社会新闻"
      },
      {
        "raw_hot": 866521,
        "num": 866521,
        "word": "千万不要用皮蛋做馄饨",
        "onboard_time": 1668935668,
        "rank": 4,
        "category": "美食"
      },
      {
        "raw_hot": 768457,
        "num": 768457,
        "word": "世界杯开幕式提前一小时",
        "onboard_time": 1668937588,
        "rank": 5,
        "category": "体育"
      },
      {
        "raw_hot": 598500,
        "num": 598500,
        "word": "32岁全职妈妈自学化妆2月气质大变",
        "onboard_time": 1668935786,
        "rank": 6,
        "category": "社会新闻"
      },
      {
        "raw_hot": 555670,
        "num": 555670,
        "word": "李峋误会朱韵结婚",
        "onboard_time": 1668932487,
        "rank": 7,
        "category": "影视"
      },
      {
        "raw_hot": 443997,
        "num": 443997,
        "word": "武汉疫情防控",
        "onboard_time": 1668924326,
        "rank": 8,
        "category": "社会新闻"
      },
      {
        "raw_hot": 421853,
        "num": 421853,
        "word": "北京疫情防控",
        "onboard_time": 1668939557,
        "rank": 9,
        "category": "社会新闻"
      },
      {
        "raw_hot": 664345,
        "num": 420875,
        "word": "郑州通报4个月大女婴夭折",
        "onboard_time": 1668938367,
        "rank": 10,
        "category": "社会新闻"
      },
      {
        "raw_hot": 418902,
        "num": 418902,
        "word": "为什么有人不喜欢过生日",
        "onboard_time": 1668935424,
        "rank": 11,
        "category": "情感"
      },
      {
        "raw_hot": 403712,
        "num": 403712,
        "word": "北京疫情发布会",
        "onboard_time": 1668935727,
        "rank": 12,
        "category": "社会新闻"
      },
      {
        "raw_hot": 389118,
        "num": 389118,
        "word": "薛之谦想看梅西拿奖杯",
        "onboard_time": 1668937709,
        "rank": 13,
        "category": "体育,艺人"
      },
      {
        "raw_hot": 370758,
        "num": 370758,
        "word": "虞书欣欧阳娜娜徐璐今日营业照",
        "onboard_time": 1668933447,
        "rank": 14,
        "category": "作品衍生"
      },
      {
        "raw_hot": 353637,
        "num": 353637,
        "word": "31省平均工资发布",
        "onboard_time": 1668937467,
        "rank": 15,
        "category": "社会新闻"
      },
      {
        "raw_hot": 351657,
        "num": 351657,
        "word": "福州警方通报轿车占车位被扔进河",
        "onboard_time": 1668935306,
        "rank": 16,
        "category": "社会新闻"
      },
      {
        "raw_hot": 336124,
        "num": 336124,
        "word": "陈飞宇片场夸张婧仪可爱",
        "onboard_time": 1668938125,
        "rank": 17,
        "category": "影视"
      },
      {
        "raw_hot": 295204,
        "num": 295204,
        "word": "金智秀晒与卡妹的合照",
        "onboard_time": 1668938607,
        "rank": 18,
        "category": "艺人"
      },
      {
        "raw_hot": 332650,
        "num": 290677,
        "word": "李峋向朱韵求婚",
        "onboard_time": 1668938848,
        "rank": 19,
        "category": "影视"
      },
      {
        "raw_hot": 483251,
        "num": 286763,
        "word": "在公厕被殴打女子回应",
        "onboard_time": 1668925167,
        "rank": 20,
        "category": "社会负面"
      },
      {
        "raw_hot": 282182,
        "num": 282182,
        "word": "南京一小区多条流浪猫接连死亡",
        "onboard_time": 1668934888,
        "rank": 21,
        "category": "社会负面"
      },
      {
        "raw_hot": 271984,
        "num": 271984,
        "word": "2父亲因炫耀孩子大打出手",
        "onboard_time": 1668924687,
        "rank": 22,
        "category": "社会负面"
      },
      {
        "raw_hot": 261040,
        "num": 261040,
        "word": "北京朝阳倡议周一继续减少流动",
        "onboard_time": 1668938546,
        "rank": 23,
        "category": "社会新闻"
      },
      {
        "raw_hot": 249448,
        "num": 249448,
        "word": "被Adele退场方式美到了",
        "onboard_time": 1668937405,
        "rank": 24,
        "category": "音乐"
      },
      {
        "raw_hot": 248137,
        "num": 248137,
        "word": "看恐怖片被吓到就这样做",
        "onboard_time": 1668934947,
        "rank": 25,
        "category": "幽默"
      },
      {
        "raw_hot": 247022,
        "num": 247022,
        "word": "内马尔预测巴西是冠军",
        "onboard_time": 1668932726,
        "rank": 26,
        "category": "体育,综艺"
      },
      {
        "raw_hot": 246969,
        "num": 246969,
        "word": "老兵立功证书上主要事迹一栏是空白",
        "onboard_time": 1668934765,
        "rank": 27,
        "category": "社会新闻,军事"
      },
      {
        "raw_hot": 243573,
        "num": 243573,
        "word": "初中生花900元文身清洗要6万",
        "onboard_time": 1668919647,
        "rank": 28,
        "category": "社会新闻"
      },
      {
        "raw_hot": 238710,
        "num": 238710,
        "word": "田柾国孙兴慜合照",
        "onboard_time": 1668936209,
        "rank": 29,
        "category": "体育,艺人"
      },
      {
        "raw_hot": 226502,
        "num": 226502,
        "word": "世界杯男模",
        "onboard_time": 1668931407,
        "rank": 30,
        "category": "体育,网红"
      },
      {
        "raw_hot": 226310,
        "num": 226310,
        "word": "北京奥运媒体包再现卡塔尔",
        "onboard_time": 1668933805,
        "rank": 31,
        "category": "体育,社会新闻"
      },
      {
        "raw_hot": 219120,
        "num": 219120,
        "word": "世界杯",
        "onboard_time": 1668907471,
        "rank": 32,
        "category": "体育"
      },
      {
        "raw_hot": 210093,
        "num": 210093,
        "word": "汪小菲深夜直播唱过火",
        "onboard_time": 1668926487,
        "rank": 33,
        "category": "艺人"
      },
      {
        "raw_hot": 209437,
        "num": 209437,
        "word": "当男朋友看了卿卿日常",
        "onboard_time": 1668929846,
        "rank": 34,
        "category": "影视"
      },
      {
        "raw_hot": 183258,
        "num": 183258,
        "word": "山西朔州有居民没做核酸就出结果",
        "onboard_time": 1668937947,
        "rank": 35,
        "category": "社会新闻"
      },
      {
        "raw_hot": 181349,
        "num": 181349,
        "word": "马斯克发布与推特员工凌晨加班照",
        "onboard_time": 1668932067,
        "rank": 36,
        "category": "科技,社会新闻"
      },
      {
        "raw_hot": 169321,
        "num": 169321,
        "word": "张柏芝紫色长裙随拍",
        "onboard_time": 1668939326,
        "rank": 37,
        "category": "艺人"
      },
      {
        "raw_hot": 158089,
        "num": 158089,
        "word": "全国医院排行榜",
        "onboard_time": 1668926246,
        "rank": 38,
        "category": "社会新闻"
      },
      {
        "raw_hot": 155395,
        "num": 155395,
        "word": "男子请工人疏通下水道被收1600元",
        "onboard_time": 1668929668,
        "rank": 39,
        "category": "社会新闻"
      },
      {
        "raw_hot": 163799,
        "num": 152288,
        "word": "鹿晗是懂解释的",
        "onboard_time": 1668932964,
        "rank": 40,
        "category": "作品衍生"
      },
      {
        "raw_hot": 144880,
        "num": 144880,
        "word": "秦施怼前男友太拼了",
        "onboard_time": 1668935367,
        "rank": 41,
        "category": "影视"
      },
      {
        "raw_hot": 126678,
        "num": 126678,
        "word": "男子用矿泉水瓶给流浪猫做猫窝",
        "onboard_time": 1668937288,
        "rank": 42,
        "category": "社会正能量"
      },
      {
        "raw_hot": 124466,
        "num": 124466,
        "word": "世界杯上满满中国设计小巧思",
        "onboard_time": 1668930987,
        "rank": 43,
        "category": "体育,社会新闻"
      },
      {
        "raw_hot": 118362,
        "num": 118362,
        "word": "马拉多纳会保佑梅西夺冠",
        "onboard_time": 1668939628,
        "rank": 44,
        "category": "体育"
      },
      {
        "raw_hot": 118048,
        "num": 118048,
        "word": "95后四小花首轮推荐结果",
        "onboard_time": 1668922527,
        "rank": 45,
        "category": "艺人"
      },
      {
        "raw_hot": 104256,
        "num": 104256,
        "word": "原来居家也能有效减肥",
        "onboard_time": 1668932307,
        "rank": 46,
        "category": "体育"
      },
      {
        "raw_hot": 111958,
        "num": 99155,
        "word": "中国球迷给梅西的迷惑建议",
        "onboard_time": 1668932784,
        "rank": 47,
        "category": "体育"
      },
      {
        "raw_hot": 91871,
        "num": 91871,
        "word": "南瓜自己滚进锅里还盖上了盖",
        "onboard_time": 1668928824,
        "rank": 48,
        "category": "社会新闻"
      },
      {
        "raw_hot": 78210,
        "num": 78210,
        "word": "当emoji学会跳kpop",
        "onboard_time": 1668927025,
        "rank": 49,
        "category": "幽默"
      }
    ],
    "hotgov": {
      "word": "#既提出中国主张又拿出中国行动#"
    }
  }
}